pymock/__init__.py
pymock/action_selector.py
pymock/argsmap.py
pymock/mock_object.py
pymock/pymock.py
pymock/action/__init__.py
pymock/action/call_action.py
pymock/action/raise_action.py
pymock/action/return_action.py
pymock/matcher/__init__.py
pymock/matcher/matcher.py
pymock/matcher/matcher_factory.py
pymock/matcher/type_matcher.py
tests/__init__.py
tests/argsmap.py
tests/test_action_selector.py
tests/test_examples.py
tests/test_mock_object.py
tests/action/__init__.py
tests/action/test_raise_action.py
tests/action/test_return_action.py
tests/matcher/__init__.py
tests/matcher/test_type_matcher.py
python_mock-0.0.3.dist-info/LICENSE
python_mock-0.0.3.dist-info/METADATA
python_mock-0.0.3.dist-info/WHEEL
python_mock-0.0.3.dist-info/top_level.txt
python_mock-0.0.3.dist-info/RECORD
