Metadata-Version: 2.1
Name: python-mock
Version: 0.0.3
Summary: Mocking in Python made easy
Home-page: https://github.com/diddi-/pymock
Author: Diddi Oskarsson
Author-email: diddi@diddi.se
License: MIT
Platform: UNKNOWN
Classifier: Programming Language :: Python :: 3
Classifier: License :: OSI Approved :: MIT License
Classifier: Operating System :: OS Independent
Requires-Python: >=3.7
